{
    "name": "Proxmox Datacenter Manager",
    "slug": "proxmox-datacenter-manager",
    "categories": [
      1
    ],
    "date_created": "2024-12-25",
    "type": "ct",
    "updateable": true,
    "privileged": false,
    "interface_port": 8443,
    "documentation": "https://pve.proxmox.com/wiki/Proxmox_Datacenter_Manager_Roadmap",
    "website": "https://pve.proxmox.com/wiki/Proxmox_Datacenter_Manager_Roadmap",
    "logo": "https://raw.githubusercontent.com/home-assistant/brands/master/core_integrations/proxmoxve/icon.png",
    "description": "The Proxmox Datacenter Manager project has been developed with the objective of providing a centralized overview of all your individual nodes and clusters. It also enables basic management like migrations of virtual guests without any cluster network requirements. ",
    "install_methods": [
      {
        "type": "default",
        "script": "ct/proxmox-datacenter-manager.sh",
        "resources": {
          "cpu": 2,
          "ram": 2048,
          "hdd": 10,
          "os": "Debian",
          "version": "12"
        }
      }
    ],
    "default_credentials": {
      "username": null,
      "password": null
    },
    "notes": [
      {
        "text": "Set a root password if using autologin. This will be the Proxmox-Datacenter-Manager password. `sudo passwd root`",
        "type": "info"
      },
      {
        "text": "Proxmox Datacenter Manager is in an alpha stage of development. Use it cautiously, as bugs, incomplete features, and potential instabilities are expected.",
        "type": "warning"
      }
    ]
  }
